Metadata-Version: 2.1
Name: kozakmegalluksi
Version: 1.1.1
Summary: A package from mr.dnd
Author: mr.dnd
Author-email: <klestianb@gmail.com>
Keywords: nemzz,kozak,mega,lluksi
Classifier: Development Status :: 1 - Planning
Classifier: Intended Audience :: Developers
Classifier: Programming Language :: Python :: 3
Classifier: Operating System :: Unix
Classifier: Operating System :: MacOS :: MacOS X
Classifier: Operating System :: Microsoft :: Windows
